{
  "project_info": {
    "project_number": "358304789487",
    "firebase_url": "https://cse5236project-7b8dd.firebaseio.com",
    "project_id": "cse5236project-7b8dd",
    "storage_bucket": "cse5236project-7b8dd.appspot.com"
  },
  "client": [
    {
      "client_info": {
        "mobilesdk_app_id": "1:358304789487:android:1d741c06eb7c6965",
        "android_client_info": {
          "package_name": "com.example.flashcardapp"
        }
      },
      "oauth_client": [
        {
          "client_id": "358304789487-tqlp39qn3ionrjm8qp3dtnsvln91c3qd.apps.googleusercontent.com",
          "client_type": 3
        }
      ],
      "api_key": [
        {
          "current_key": "AIzaSyDHxVB6lj6t_MEEKsZQBwWHMioVuSmqO18"
        }
      ],
      "services": {
        "analytics_service": {
          "status": 1
        },
        "appinvite_service": {
          "status": 1,
          "other_platform_oauth_client": []
        },
        "ads_service": {
          "status": 2
        }
      }
    }
  ],
  "configuration_version": "1"
}